faster_fifo.cpython-312-i386-linux-musl.so
faster_fifo.libs/libgcc_s-1257a076.so.1
faster_fifo.libs/libstdc++-0530927c.so.6.0.32
faster_fifo_reduction/__init__.py
faster_fifo-1.5.2.dist-info/top_level.txt
faster_fifo-1.5.2.dist-info/RECORD
faster_fifo-1.5.2.dist-info/LICENSE
faster_fifo-1.5.2.dist-info/METADATA
faster_fifo-1.5.2.dist-info/WHEEL
