Metadata-Version: 2.1
Name: faster-fifo
Version: 1.5.2
Summary: A faster alternative to Python's standard multiprocessing.Queue (IPC FIFO queue)
Author: Aleksei Petrenko, Tushar Kumar
License: MIT
Project-URL: homepage, https://github.com/alex-petrenko/faster-fifo
Keywords: multiprocessing,data structures
Requires-Python: >=3.9
License-File: LICENSE
Provides-Extra: dev
Requires-Dist: twine; extra == "dev"
Requires-Dist: numpy<2.0,>=1.18.1; extra == "dev"
